print_package/__init__.py
print_package/print.py
print123456-0.0.1.dist-info/LICENSE.py
print123456-0.0.1.dist-info/METADATA
print123456-0.0.1.dist-info/WHEEL
print123456-0.0.1.dist-info/top_level.txt
print123456-0.0.1.dist-info/RECORD
