Metadata-Version: 2.1
Name: print123456
Version: 0.0.1
Summary: A simple printer of 6 numbers lists
Home-page: http://www.baidu.com
Author: charleyzheng
Author-email: 3216057905@qq.com
Project-URL: Bug Tracker, https://github.com/pypa/sampleproject/issues
Classifier: Programming Language :: Python :: 3
Classifier: License :: OSI Approved :: MIT License
Classifier: Operating System :: OS Independent
Requires-Python: >=3.6
License-File: LICENSE.py
